azure/ai/vision/imageanalysis/__init__.py
azure/ai/vision/imageanalysis/_client.py
azure/ai/vision/imageanalysis/_configuration.py
azure/ai/vision/imageanalysis/_model_base.py
azure/ai/vision/imageanalysis/_patch.py
azure/ai/vision/imageanalysis/_serialization.py
azure/ai/vision/imageanalysis/_vendor.py
azure/ai/vision/imageanalysis/_version.py
azure/ai/vision/imageanalysis/py.typed
azure/ai/vision/imageanalysis/_operations/__init__.py
azure/ai/vision/imageanalysis/_operations/_operations.py
azure/ai/vision/imageanalysis/_operations/_patch.py
azure/ai/vision/imageanalysis/aio/__init__.py
azure/ai/vision/imageanalysis/aio/_client.py
azure/ai/vision/imageanalysis/aio/_configuration.py
azure/ai/vision/imageanalysis/aio/_patch.py
azure/ai/vision/imageanalysis/aio/_vendor.py
azure/ai/vision/imageanalysis/aio/_operations/__init__.py
azure/ai/vision/imageanalysis/aio/_operations/_operations.py
azure/ai/vision/imageanalysis/aio/_operations/_patch.py
azure/ai/vision/imageanalysis/models/__init__.py
azure/ai/vision/imageanalysis/models/_enums.py
azure/ai/vision/imageanalysis/models/_models.py
azure/ai/vision/imageanalysis/models/_patch.py
azure_ai_vision_imageanalysis-1.0.0.dist-info/LICENSE
azure_ai_vision_imageanalysis-1.0.0.dist-info/METADATA
azure_ai_vision_imageanalysis-1.0.0.dist-info/WHEEL
azure_ai_vision_imageanalysis-1.0.0.dist-info/top_level.txt
azure_ai_vision_imageanalysis-1.0.0.dist-info/RECORD
